[
  {
    "Telefono": "9116109966",
    "Nombre": "Antone Twigg",
    "Direccion": "8 Merrick Terrace"
  },
  {
    "Telefono": "5926597128",
    "Nombre": "Ram Dalglish",
    "Direccion": "14712 Division Street"
  },
  {
    "Telefono": "7049622367",
    "Nombre": "Jehu Redpath",
    "Direccion": "42 Emmet Hill"
  },
  {
    "Telefono": "9537809930",
    "Nombre": "Ingrim Josse",
    "Direccion": "69 Hoard Way"
  },
  {
    "Telefono": "1021164682",
    "Nombre": "Rasia Kerner",
    "Direccion": "8 Cascade Center"
  },
  {
    "Telefono": "7876486882",
    "Nombre": "Herta Thorouggood",
    "Direccion": "0 Charing Cross Way"
  },
  {
    "Telefono": "1717713011",
    "Nombre": "Lynnett Braidley",
    "Direccion": "61 Buell Park"
  },
  {
    "Telefono": "1859825237",
    "Nombre": "Delcina Sibun",
    "Direccion": "10 Park Meadow Plaza"
  },
  {
    "Telefono": "2254619885",
    "Nombre": "Danny Keemer",
    "Direccion": "66 Mifflin Avenue"
  },
  {
    "Telefono": "6849199082",
    "Nombre": "Olivia Shalcros",
    "Direccion": "880 Hollow Ridge Road"
  },
  {
    "Telefono": "6192178400",
    "Nombre": "Cointon Pyke",
    "Direccion": "59037 Jenna Terrace"
  },
  {
    "Telefono": "2668321403",
    "Nombre": "Elwyn Allans",
    "Direccion": "46495 Caliangt Plaza"
  },
  {
    "Telefono": "5345858723",
    "Nombre": "Sela Garric",
    "Direccion": "5146 Onsgard Drive"
  },
  {
    "Telefono": "1755403963",
    "Nombre": "Evy Innes",
    "Direccion": "4 Erie Place"
  },
  {
    "Telefono": "2233731391",
    "Nombre": "Gwenore Burgess",
    "Direccion": "7 Forster Center"
  },
  {
    "Telefono": "2433793066",
    "Nombre": "Milton Vakhrushin",
    "Direccion": "000 Marcy Junction"
  },
  {
    "Telefono": "1275467118",
    "Nombre": "Jania Lanbertoni",
    "Direccion": "22867 Kenwood Parkway"
  },
  {
    "Telefono": "9484200553",
    "Nombre": "Joane Mulroy",
    "Direccion": "523 Jay Hill"
  },
  {
    "Telefono": "5708458345",
    "Nombre": "Tani Brownsmith",
    "Direccion": "70007 Dakota Place"
  },
  {
    "Telefono": "3511948742",
    "Nombre": "Timmie Darrington",
    "Direccion": "512 Porter Lane"
  },
  {
    "Telefono": "3259795587",
    "Nombre": "Kathy Wasson",
    "Direccion": "8482 Portage Hill"
  },
  {
    "Telefono": "3809572889",
    "Nombre": "Gasparo Polgreen",
    "Direccion": "7930 Caliangt Center"
  },
  {
    "Telefono": "3347266008",
    "Nombre": "Juditha Poundford",
    "Direccion": "40 Farmco Parkway"
  },
  {
    "Telefono": "8624621152",
    "Nombre": "Karoly Hattigan",
    "Direccion": "08732 Northview Court"
  },
  {
    "Telefono": "5942638052",
    "Nombre": "Ara Rickardsson",
    "Direccion": "0770 Heffernan Center"
  },
  {
    "Telefono": "9977112116",
    "Nombre": "Aron de Keyser",
    "Direccion": "6 Holmberg Point"
  },
  {
    "Telefono": "5596311583",
    "Nombre": "Stern Petrazzi",
    "Direccion": "43369 Gateway Parkway"
  },
  {
    "Telefono": "4228533618",
    "Nombre": "Abby Fardoe",
    "Direccion": "6 Ohio Court"
  },
  {
    "Telefono": "5062151382",
    "Nombre": "Shari Phripp",
    "Direccion": "6730 Bellgrove Way"
  },
  {
    "Telefono": "7425449236",
    "Nombre": "Cordie Kitchenham",
    "Direccion": "27529 Jackson Trail"
  },
  {
    "Telefono": "7371845041",
    "Nombre": "Constantine Moutray Read",
    "Direccion": "730 Briar Crest Trail"
  },
  {
    "Telefono": "8832872257",
    "Nombre": "Kali Vedekhov",
    "Direccion": "9796 Sugar Hill"
  },
  {
    "Telefono": "3975428865",
    "Nombre": "Clarance Smitheram",
    "Direccion": "47 Merchant Plaza"
  },
  {
    "Telefono": "3207214334",
    "Nombre": "Adelice Hampton",
    "Direccion": "85 Vahlen Terrace"
  },
  {
    "Telefono": "9206518783",
    "Nombre": "Wilhelmine Breedy",
    "Direccion": "88 Jay Road"
  },
  {
    "Telefono": "6924134778",
    "Nombre": "Natka Wyett",
    "Direccion": "34 Westridge Court"
  },
  {
    "Telefono": "6115607147",
    "Nombre": "Georgie Toopin",
    "Direccion": "8276 Quincy Hill"
  },
  {
    "Telefono": "6567503962",
    "Nombre": "Una Flewan",
    "Direccion": "275 Morrow Crossing"
  },
  {
    "Telefono": "9691703452",
    "Nombre": "Melisa Cappell",
    "Direccion": "81 Northland Trail"
  },
  {
    "Telefono": "5994932871",
    "Nombre": "Elvina Naisbet",
    "Direccion": "21747 Ridgeview Hill"
  },
  {
    "Telefono": "8199440031",
    "Nombre": "Violette Dockree",
    "Direccion": "40 Pawling Drive"
  },
  {
    "Telefono": "6009396704",
    "Nombre": "Bailie Philler",
    "Direccion": "25013 Lakewood Gardens Street"
  },
  {
    "Telefono": "2138048411",
    "Nombre": "Victoir Lytell",
    "Direccion": "4841 Huxley Circle"
  },
  {
    "Telefono": "3388651777",
    "Nombre": "Mathias Dmytryk",
    "Direccion": "601 Basil Drive"
  },
  {
    "Telefono": "3372941409",
    "Nombre": "Payton Mahy",
    "Direccion": "57647 Garrison Park"
  },
  {
    "Telefono": "2571376669",
    "Nombre": "Cass Tollerton",
    "Direccion": "0 Pennsylvania Parkway"
  },
  {
    "Telefono": "5971305344",
    "Nombre": "Hal Growcock",
    "Direccion": "254 Hanover Drive"
  },
  {
    "Telefono": "1997775681",
    "Nombre": "Bourke Strotton",
    "Direccion": "44 Forest Center"
  },
  {
    "Telefono": "3512519360",
    "Nombre": "Donnie Hiddersley",
    "Direccion": "77 Chive Park"
  },
  {
    "Telefono": "6409761138",
    "Nombre": "Garek Cropper",
    "Direccion": "0746 Browning Street"
  }
]